{"$type":"List`1","$values":[{"$id":"1","$type":"ProjectOptionEntry","key":"NetworkCollapsed","context":"{2232342-1563}","value":false},{"$id":"2","$type":"ProjectOptionEntry","key":"RestoreNetworkStates","context":"{2232321-1553}","value":true},{"$id":"3","$type":"ProjectOptionEntry","key":"NetworkCollapsed","context":"{2232342-2317}","value":false},{"$id":"4","$type":"ProjectOptionEntry","key":"RestoreNetworkStates","context":"{2232321-2311}","value":true},{"$id":"5","$type":"ProjectOptionEntry","key":"NetworkCollapsed","context":"{2232342-2346}","value":false},{"$id":"6","$type":"ProjectOptionEntry","key":"NetworkCollapsed","context":"{2232342-2471}","value":false},{"$id":"7","$type":"ProjectOptionEntry","key":"NetworkCollapsed","context":"{2232342-2472}","value":false},{"$id":"8","$type":"ProjectOptionEntry","key":"NetworkCollapsed","context":"{2232342-2473}","value":false},{"$id":"9","$type":"ProjectOptionEntry","key":"LastSelection@Siemens.Simatic.PlcLanguages.PLFrame.BasicLanguageEditor","context":"{2232321-1553}","value":{"$id":"10","$type":"SessionState","NetworkStates":{"$id":"11","$type":"Dictionary`2","3":5},"FocusedComponent":4,"ComponentUndoState":{"$id":"12","$type":"FLGViewSessionState","SelectedElements":{"$type":"String[]","$values":["<?xml version=\"1.0\" encoding=\"utf-16\"?><Operand UId=\"40\" RefId=\"13\" OwnerUId=\"39\" ParaNum=\"-1\" Formalname=\"operand\" />"]},"RelevantSettings":null}}},{"$id":"13","$type":"ProjectOptionEntry","key":"LastSelection@Siemens.Simatic.PlcLanguages.PLFrame.BasicLanguageEditor","context":"{2232321-2311}","value":{"$id":"14","$type":"SessionState","NetworkStates":{"$id":"15","$type":"Dictionary`2","1":5},"FocusedComponent":4,"ComponentUndoState":{"$id":"16","$type":"FLGViewSessionState","SelectedElements":{"$type":"String[]","$values":["<?xml version=\"1.0\" encoding=\"utf-16\"?><Operand UId=\"23\" RefId=\"2\" OwnerUId=\"22\" ParaNum=\"-1\" Formalname=\"operand\" />"]},"RelevantSettings":null}}}]}